FailoverCache/__init__.py
failovercache-1.0.0.dist-info/licenses/LICENSE
failovercache-1.0.0.dist-info/METADATA
failovercache-1.0.0.dist-info/WHEEL
failovercache-1.0.0.dist-info/top_level.txt
failovercache-1.0.0.dist-info/RECORD
