Metadata-Version: 2.4
Name: FailoverCache
Version: 1.0.0
Summary: A flexible Python cache system with automatic fallback to disk when Redis is unavailable
Author-email: Endkind <endkind.ender@endkind.net>
License: MIT License
Classifier: Programming Language :: Python :: 3
Classifier: License :: OSI Approved :: MIT License
Classifier: Operating System :: OS Independent
Classifier: Intended Audience :: Developers
Classifier: Topic :: Software Development :: Libraries
Requires-Python: >=3.9
License-File: LICENSE
Requires-Dist: redis>=6.2.0
Requires-Dist: diskcache>=5.6.3
Dynamic: license-file
